docubox/__init__.py
docubox/__main__.py
docubox/builder.py
docubox/config.py
docubox/launcher.py
docubox/version.py
docubox-0.2.1.dist-info/LICENSE
docubox-0.2.1.dist-info/METADATA
docubox-0.2.1.dist-info/WHEEL
docubox-0.2.1.dist-info/top_level.txt
docubox-0.2.1.dist-info/RECORD
