Metadata-Version: 2.1
Name: docubox
Version: 0.2.1
Summary: single busybox like binary for document solutions
Author-email: Hiroshi Miura <miurahr@linux.com>
License: BSD 2-Clause "Simplified" License
Keywords: mkdocs,sphinx,babel,PyInstaller
Classifier: Development Status :: 3 - Alpha
Classifier: License :: OSI Approved :: BSD License
Classifier: Operating System :: MacOS :: MacOS X
Classifier: Operating System :: Microsoft :: Windows
Classifier: Operating System :: POSIX
Classifier: Operating System :: POSIX :: Linux
Classifier: Programming Language :: Python :: 3.11
Requires-Python: >=3.11
License-File: LICENSE
Requires-Dist: mkdocs (==1.4.2)
Requires-Dist: mkdocs-material (==8.5.11)
Requires-Dist: mkdocs-plantuml (==0.1.1)
Requires-Dist: mkdocs-alabaster (==0.8.0)
Requires-Dist: mkdocs-custommill (==1.3.0)
Requires-Dist: mkdocs-badges (==0.4.0)
Requires-Dist: mkdocs-coverage (==0.2.6)
Requires-Dist: lunr (==0.6.2)
Requires-Dist: PyInstaller (==5.7.0)
Requires-Dist: PyYAML (==6.0)
Requires-Dist: Sphinx (==5.3.0)
Requires-Dist: sphinx-intl (==2.0.1)
Requires-Dist: babel (==2.11.0)
Requires-Dist: myst-parser (==0.18.1)
Requires-Dist: markdown-it-py (==2.1.0)
Requires-Dist: linkify-it-py (==2.0.0)
Requires-Dist: sphinxcontrib-ditaa (==1.0.2)
Requires-Dist: sphinxcontrib-drawio (==0.0.16)
Requires-Dist: sphinxcontrib-httpdomain (==1.8.1)
Requires-Dist: sphinxcontrib-imagesvg (==0.1)
Requires-Dist: sphinxcontrib-openapi (==0.7.0)
Requires-Dist: sphinxcontrib-plantuml (==0.24.1)
Requires-Dist: sphinxcontrib-svgbob (==0.2.1)
Requires-Dist: sphinxcontrib-redoc (==1.6.0)
Requires-Dist: sphinxcontrib-xlsxtable (==1.0.0)
Requires-Dist: sphinxcontrib-websupport (==1.2.4)
Requires-Dist: sphinxcontrib-youtube (==1.2.0)
Requires-Dist: sphinxemoji (==0.2.0)
Requires-Dist: sphinx-bootstrap-theme (==0.8.1)
Requires-Dist: sphinx-rtd-theme (==1.1.1)
Requires-Dist: jinja2[i18n] (==3.1.2)
Requires-Dist: j2cli (==0.3.10)
Requires-Dist: pygments-style-kit (==1.0.1)
